docs/Makefile
docs/make.bat
docs/requirements.txt
docs/source/Other.rst
docs/source/README.rst
docs/source/conf.py
docs/source/image.jpg
docs/source/index.rst
pdemo/__init__.py
pdemo/__main__.py
pdemo/_version.py
pdemo/ext.rst
pdemo/src/__init__.py
pdemo/src/add.py
pdemo/tests/__init__.py
pdemo/tests/test_1.py
linlei04_pdemo-1.0.1.dist-info/LICENSE
linlei04_pdemo-1.0.1.dist-info/METADATA
linlei04_pdemo-1.0.1.dist-info/WHEEL
linlei04_pdemo-1.0.1.dist-info/entry_points.txt
linlei04_pdemo-1.0.1.dist-info/top_level.txt
linlei04_pdemo-1.0.1.dist-info/RECORD
