Metadata-Version: 2.1
Name: linlei04-pdemo
Version: 1.0.1
Summary: My package description
Author-email: xmlclone <xmlclone@gmail.com>
License: MIT
Project-URL: Homepage, https://github.com/xmlclone/pdemo
Project-URL: Documentation, https://github.com/xmlclone/pdemo
Project-URL: Code, https://github.com/xmlclone/pdemo
Project-URL: Help/Questions, https://github.com/xmlclone/pdemo
Project-URL: Issue tracker, https://github.com/xmlclone/pdemo
Classifier: Programming Language :: Python
Classifier: Programming Language :: Python :: 3
Classifier: Programming Language :: Python :: 3.8
Classifier: Programming Language :: Python :: 3.9
Classifier: Programming Language :: Python :: 3.10
Classifier: Programming Language :: Python :: 3.11
Classifier: Programming Language :: Python :: 3.12
Requires-Python: >=3.7
License-File: LICENSE
Requires-Dist: requests
Requires-Dist: selenium ==4.14.0
